{
  "openapi": "3.0.4",
  "info": {
    "title": "Service, Version=1.0.0.0, Culture=neutral, PublicKeyToken=null",
    "version": "1.0"
  },
  "paths": {
    "/Cluster": {
      "get": {
        "tags": [
          "Cluster"
        ],
        "operationId": "GetAllClusterId",
        "responses": {
          "200": {
            "description": "OK",
            "content": {
              "application/json": {
                "schema": {
                  "type": "array",
                  "items": {
                    "type": "string",
                    "format": "uuid"
                  }
                }
              }
            }
          }
        }
      },
      "post": {
        "tags": [
          "Cluster"
        ],
        "operationId": "PostCluster",
        "requestBody": {
          "content": {
            "application/json": {
              "schema": {
                "$ref": "#/components/schemas/NORCE.Drilling.Cluster.Model.Cluster"
              }
            },
            "text/json": {
              "schema": {
                "$ref": "#/components/schemas/NORCE.Drilling.Cluster.Model.Cluster"
              }
            },
            "application/*+json": {
              "schema": {
                "$ref": "#/components/schemas/NORCE.Drilling.Cluster.Model.Cluster"
              }
            }
          }
        },
        "responses": {
          "200": {
            "description": "OK"
          }
        }
      }
    },
    "/Cluster/MetaInfo": {
      "get": {
        "tags": [
          "Cluster"
        ],
        "operationId": "GetAllClusterMetaInfo",
        "responses": {
          "200": {
            "description": "OK",
            "content": {
              "application/json": {
                "schema": {
                  "type": "array",
                  "items": {
                    "$ref": "#/components/schemas/OSDC.DotnetLibraries.General.DataManagement.MetaInfo"
                  }
                }
              }
            }
          }
        }
      }
    },
    "/Cluster/{id}": {
      "get": {
        "tags": [
          "Cluster"
        ],
        "operationId": "GetClusterById",
        "parameters": [
          {
            "name": "id",
            "in": "path",
            "required": true,
            "schema": {
              "type": "string",
              "format": "uuid"
            }
          }
        ],
        "responses": {
          "200": {
            "description": "OK",
            "content": {
              "application/json": {
                "schema": {
                  "$ref": "#/components/schemas/NORCE.Drilling.Cluster.Model.Cluster"
                }
              }
            }
          }
        }
      },
      "put": {
        "tags": [
          "Cluster"
        ],
        "operationId": "PutClusterById",
        "parameters": [
          {
            "name": "id",
            "in": "path",
            "required": true,
            "schema": {
              "type": "string",
              "format": "uuid"
            }
          }
        ],
        "requestBody": {
          "content": {
            "application/json": {
              "schema": {
                "$ref": "#/components/schemas/NORCE.Drilling.Cluster.Model.Cluster"
              }
            },
            "text/json": {
              "schema": {
                "$ref": "#/components/schemas/NORCE.Drilling.Cluster.Model.Cluster"
              }
            },
            "application/*+json": {
              "schema": {
                "$ref": "#/components/schemas/NORCE.Drilling.Cluster.Model.Cluster"
              }
            }
          }
        },
        "responses": {
          "200": {
            "description": "OK"
          }
        }
      },
      "delete": {
        "tags": [
          "Cluster"
        ],
        "operationId": "DeleteClusterById",
        "parameters": [
          {
            "name": "id",
            "in": "path",
            "required": true,
            "schema": {
              "type": "string",
              "format": "uuid"
            }
          }
        ],
        "responses": {
          "200": {
            "description": "OK"
          }
        }
      }
    },
    "/Cluster/HeavyData": {
      "get": {
        "tags": [
          "Cluster"
        ],
        "operationId": "GetAllCluster",
        "responses": {
          "200": {
            "description": "OK",
            "content": {
              "application/json": {
                "schema": {
                  "type": "array",
                  "items": {
                    "$ref": "#/components/schemas/NORCE.Drilling.Cluster.Model.Cluster"
                  }
                }
              }
            }
          }
        }
      }
    },
    "/ClusterUsageStatistics": {
      "get": {
        "tags": [
          "ClusterUsageStatistics"
        ],
        "operationId": "GetClusterUsageStatistics",
        "responses": {
          "200": {
            "description": "OK",
            "content": {
              "application/json": {
                "schema": {
                  "$ref": "#/components/schemas/NORCE.Drilling.Cluster.Model.UsageStatisticsCluster"
                }
              }
            }
          }
        }
      }
    }
  },
  "components": {
    "schemas": {
      "NORCE.Drilling.Cluster.Model.Cluster": {
        "type": "object",
        "properties": {
          "MetaInfo": {
            "$ref": "#/components/schemas/OSDC.DotnetLibraries.General.DataManagement.MetaInfo"
          },
          "Name": {
            "type": "string",
            "nullable": true
          },
          "Description": {
            "type": "string",
            "nullable": true
          },
          "CreationDate": {
            "type": "string",
            "format": "date-time",
            "nullable": true
          },
          "LastModificationDate": {
            "type": "string",
            "format": "date-time",
            "nullable": true
          },
          "FieldID": {
            "type": "string",
            "format": "uuid",
            "nullable": true
          },
          "IsSingleWell": {
            "type": "boolean"
          },
          "RigID": {
            "type": "string",
            "format": "uuid",
            "nullable": true
          },
          "IsFixedPlatform": {
            "type": "boolean"
          },
          "ReferenceLatitude": {
            "$ref": "#/components/schemas/OSDC.DotnetLibraries.Drilling.DrillingProperties.GaussianDrillingProperty"
          },
          "ReferenceLongitude": {
            "$ref": "#/components/schemas/OSDC.DotnetLibraries.Drilling.DrillingProperties.GaussianDrillingProperty"
          },
          "ReferenceDepth": {
            "$ref": "#/components/schemas/OSDC.DotnetLibraries.Drilling.DrillingProperties.GaussianDrillingProperty"
          },
          "GroundMudLineDepth": {
            "$ref": "#/components/schemas/OSDC.DotnetLibraries.Drilling.DrillingProperties.GaussianDrillingProperty"
          },
          "TopWaterDepth": {
            "$ref": "#/components/schemas/OSDC.DotnetLibraries.Drilling.DrillingProperties.GaussianDrillingProperty"
          },
          "Slots": {
            "type": "object",
            "additionalProperties": {
              "$ref": "#/components/schemas/NORCE.Drilling.Cluster.Model.Slot"
            },
            "nullable": true
          }
        },
        "additionalProperties": false
      },
      "NORCE.Drilling.Cluster.Model.CountPerDay": {
        "type": "object",
        "properties": {
          "Date": {
            "type": "string",
            "format": "date-time"
          },
          "Count": {
            "type": "integer",
            "format": "int64"
          }
        },
        "additionalProperties": false
      },
      "NORCE.Drilling.Cluster.Model.History": {
        "type": "object",
        "properties": {
          "Data": {
            "type": "array",
            "items": {
              "$ref": "#/components/schemas/NORCE.Drilling.Cluster.Model.CountPerDay"
            },
            "nullable": true
          }
        },
        "additionalProperties": false
      },
      "NORCE.Drilling.Cluster.Model.Slot": {
        "type": "object",
        "properties": {
          "ID": {
            "type": "string",
            "format": "uuid"
          },
          "Name": {
            "type": "string",
            "nullable": true
          },
          "Description": {
            "type": "string",
            "nullable": true
          },
          "CreationDate": {
            "type": "string",
            "format": "date-time",
            "nullable": true
          },
          "LastModificationDate": {
            "type": "string",
            "format": "date-time",
            "nullable": true
          },
          "Latitude": {
            "$ref": "#/components/schemas/OSDC.DotnetLibraries.Drilling.DrillingProperties.GaussianDrillingProperty"
          },
          "Longitude": {
            "$ref": "#/components/schemas/OSDC.DotnetLibraries.Drilling.DrillingProperties.GaussianDrillingProperty"
          }
        },
        "additionalProperties": false
      },
      "NORCE.Drilling.Cluster.Model.UsageStatisticsCluster": {
        "type": "object",
        "properties": {
          "LastSaved": {
            "type": "string",
            "format": "date-time"
          },
          "BackUpInterval": {
            "type": "string",
            "format": "date-span"
          },
          "GetAllClusterIdPerDay": {
            "$ref": "#/components/schemas/NORCE.Drilling.Cluster.Model.History"
          },
          "GetAllClusterMetaInfoPerDay": {
            "$ref": "#/components/schemas/NORCE.Drilling.Cluster.Model.History"
          },
          "GetClusterByIdPerDay": {
            "$ref": "#/components/schemas/NORCE.Drilling.Cluster.Model.History"
          },
          "GetAllClusterPerDay": {
            "$ref": "#/components/schemas/NORCE.Drilling.Cluster.Model.History"
          },
          "PostClusterPerDay": {
            "$ref": "#/components/schemas/NORCE.Drilling.Cluster.Model.History"
          },
          "PutClusterByIdPerDay": {
            "$ref": "#/components/schemas/NORCE.Drilling.Cluster.Model.History"
          },
          "DeleteClusterByIdPerDay": {
            "$ref": "#/components/schemas/NORCE.Drilling.Cluster.Model.History"
          }
        },
        "additionalProperties": false
      },
      "OSDC.DotnetLibraries.Drilling.DrillingProperties.GaussianDrillingProperty": {
        "type": "object",
        "properties": {
          "GaussianValue": {
            "$ref": "#/components/schemas/OSDC.DotnetLibraries.General.Statistics.GaussianDistribution"
          }
        },
        "additionalProperties": false
      },
      "OSDC.DotnetLibraries.General.DataManagement.MetaInfo": {
        "type": "object",
        "properties": {
          "ID": {
            "type": "string",
            "format": "uuid"
          },
          "HttpHostName": {
            "type": "string",
            "nullable": true
          },
          "HttpHostBasePath": {
            "type": "string",
            "nullable": true
          },
          "HttpEndPoint": {
            "type": "string",
            "nullable": true
          }
        },
        "additionalProperties": false
      },
      "OSDC.DotnetLibraries.General.Statistics.GaussianDistribution": {
        "type": "object",
        "properties": {
          "MinValue": {
            "type": "number",
            "format": "double"
          },
          "MaxValue": {
            "type": "number",
            "format": "double"
          },
          "Mean": {
            "type": "number",
            "format": "double",
            "nullable": true
          },
          "StandardDeviation": {
            "type": "number",
            "format": "double",
            "nullable": true
          }
        },
        "additionalProperties": false
      }
    }
  }
}